arya/__init__.py
arya/channel/__init__.py
arya/channel/channel.py
arya/channel/client.py
arya/channel/registry.py
arya/errors.py
arya/segment/__init__.py
arya/segment/encoder.py
arya/segment/splitter.py
arya/segment/validator.py
arya/segment/writer.py
arya/telem/__init__.py
arya/telem/numpy.py
arya/util/__init__.py
arya/util/notification.py
arya_client-0.1.0.dist-info/WHEEL
arya_client-0.1.0.dist-info/METADATA
arya_client-0.1.0.dist-info/RECORD
